{
  "name": {
    "tr": "Yapay Zeka Kişsel Asistan"
  },
  "status": "play",
  "category": "",
  "id": "nnlmkp2elm",
  "url": "",
  "path": "yapayzekakisselasistan",
  "index": 2,
  "desing": {
    "header": [],
    "body": [],
    "footer": []
  },
  "pathnext": "",
  "description": {
    "tr": ""
  },
  "keyword": {
    "tr": ""
  },
  "text": {
    "tr": "<h1>Yapay Zeka Kişisel Asistan</h1>\n\n<div>\nGünümüzde bireysel verimlilik, zaman yönetimi ve dijital entegrasyon, profesyonel ve özel hayatımızın ayrılmaz birer parçası hâline gelmiştir. Soydan Aksoy olarak sunduğumuz “Yapay Zeka Kişisel Asistan” hizmetimiz; teknolojiyle insan odaklı çözümleri bir araya getirerek, her bireyin iş ve özel yaşamında daha akıllı, hızlı ve etkili kararlar almasını sağlar.\n\nYapay Zeka Kişisel Asistan çözümlerimiz; ajanda takibi, toplantı hatırlatmaları, e-posta ve mesaj yönetimi, sesli komutlarla işlem gerçekleştirme, analiz yapma, önerilerde bulunma, yolculuk ve rezervasyon planlama gibi birçok özelliği barındırır. Ayrıca kişisel asistanlar, kullanıcıların alışkanlıklarını öğrenerek kendini geliştirir ve kişiselleştirilmiş deneyimler sunar.\n\nBu hizmetimiz, bireylerin gün içinde yaptıkları manuel işlemleri otomatikleştirerek zaman kazandırır, hata payını düşürür ve dikkat dağınıklığını önler. Her sektöre özel modüllerle geliştirilebilen yapay zeka destekli bu asistanlar, mobil ve masaüstü platformlarla entegre çalışarak size gerçek anlamda dijital bir sekreter sağlar.\n</div>\n\n<h2>Yapay Zeka Kişisel Asistan Neler Sunar?</h2>\n<div>\n<ul>\n  <li><strong>Ajanda ve Takvim Yönetimi:</strong> Günlük görevlerinizi planlar, toplantılarınızı otomatik olarak takvime ekler ve sizi zamanında bilgilendirir.</li>\n  <li><strong>E-Posta ve Mesaj Entegrasyonu:</strong> Gmail, Outlook ve diğer e-posta servisleriyle entegre çalışır, gelen kutunuzu analiz eder, önemli e-postaları öne çıkarır ve gereksiz postaları filtreler.</li>\n  <li><strong>Sesli Komut ve Doğal Dil İşleme:</strong> Size özel geliştirilen sesli komut altyapısı sayesinde konuşarak komut verebilirsiniz. Türkçe doğal dil işleme desteğiyle anlama kabiliyeti yüksektir.</li>\n  <li><strong>Yapay Zeka Destekli Not Alma:</strong> Görüşmelerden ve toplantılardan anlık olarak not çıkarabilir, bu notları kategorize ederek kaydedebilir.</li>\n  <li><strong>Günlük Raporlama:</strong> Gün sonunda tüm aktivitelerinizi özetleyen raporlar sunar. Zamanınızı en verimli şekilde nasıl kullandığınızı analiz eder.</li>\n  <li><strong>Alışkanlık Bazlı Öğrenme:</strong> Sizi zamanla tanır. Hangi saatlerde daha üretken olduğunuzu bilir, randevularınızı bu saatlere göre optimize eder.</li>\n  <li><strong>Yolculuk ve Seyahat Planlama:</strong> Uçak bileti, otel rezervasyonu, taksi çağırma gibi işlemleri sizin adınıza gerçekleştirir.</li>\n  <li><strong>Kişisel Veri Güvenliği:</strong> Tüm verileriniz şifrelenir ve üçüncü taraflarla paylaşılmaz. ISO 27001 Bilgi Güvenliği standartlarına tam uyumludur.</li>\n</ul>\n</div>\n\n<h2>Neden Bizi Tercih Etmelisiniz?</h2>\n<div>\nSoydan Aksoy, yalnızca bir yazılım sağlayıcısı değil, aynı zamanda markaların ve bireylerin dijital dönüşüm yolculuğundaki yol arkadaşıdır. Yapay Zeka Kişisel Asistan hizmetimiz, standart yazılımların çok ötesine geçerek, her kullanıcıya özel olarak şekillenen akıllı çözümler sunar. Bizimle çalıştığınızda yalnızca bir teknoloji değil, stratejik düşünce, yaratıcı tasarım ve iş zekâsı bir araya gelir.\n\n<ul>\n  <li><strong>Özelleştirilebilirlik:</strong> İhtiyaçlarınıza göre tasarlanan ve size özel çalışan asistan sistemleri.</li>\n  <li><strong>Entegre Dijital Ekosistem:</strong> CRM, ERP, Takvim, Mesajlaşma ve Mobil uygulama entegrasyonlarıyla uçtan uca çözüm.</li>\n  <li><strong>Deneyimli Danışmanlık:</strong> Alanında uzman yapay zeka mühendisleri ve marka stratejistlerinden oluşan bir ekip.</li>\n  <li><strong>Yasal Uyumluluk:</strong> KVKK ve GDPR gibi yerel ve uluslararası veri koruma standartlarına tam uyum.</li>\n  <li><strong>7/24 Destek:</strong> Sorunlarınıza anlık çözümler, canlı destek ve kullanıcı eğitimleriyle sürdürülebilir kullanım.</li>\n</ul>\n</div>\n\n<h2>Kimler İçin Uygundur?</h2>\n<div>\nYapay Zeka Kişisel Asistan hizmetimiz; CEO'lar, yöneticiler, girişimciler, dijital içerik üreticileri, danışmanlar, freelance çalışanlar ve çok daha fazlası için uygundur. Zamanı verimli kullanmak, operasyonel süreçleri hızlandırmak ve iş yükünü azaltmak isteyen herkes bu sistemden faydalanabilir.\n</div>\n\n<h2>Geleceğin Teknolojisine Bugünden Sahip Olun</h2>\n<div>\nZamandan tasarruf etmek, daha üretken olmak ve dijital dünyada bir adım önde yer almak istiyorsanız, yapay zeka kişisel asistan hizmetimiz tam size göre. Geleceğin çalışma modelini bugünden benimsemek için bizimle iletişime geçin. Size özel demo ve analiz sunumlarımızla başlayalım.\n</div>\n\n<span>#YapayZekaAsistan #KişiselAsistan #DijitalAsistan #ZamanYönetimi #YapayZekaHizmeti #SoydanAksoyAjans #DijitalDönüşüm #AkıllıAsistan #AICompanion #AjandaYönetimi #VerimlilikArttırıcı #YapayZekaUygulaması #KişiselSekreter #YapayZekaEntegrasyonu</span>"
  },
  "spot": {
    "tr": ""
  },
  "update": "2025-08-08T04:43:39.307Z",
  "date": "2025-06-23T11:07:02.129Z",
  "img": "i4ftk.png",
  "desc": {}
}